[
  {"time": "0:28", "line": "시간을 좀 가져요"},
  {"time": "0:32", "line": "잠시만 안녕해요"},
  {"time": "0:36", "line": "사랑도 가끔 쉬어야죠"},
  {"time": "0:42", "line": "서로를 놓아주고 잠시 한숨 돌리면"},
  {"time": "0:49.8", "line": "더 나아지겠죠"},
  
  {"time": "0:54", "line": "우리 그러면 정말 그러면"},
  {"time": "0:57", "line": "더욱 깊어질 줄 알았죠"},
  {"time": "1:01", "line": "사랑은 훨씬 커질 줄로 믿었죠"},
  
  {"time": "1:07.5", "line": "떠나갈 줄은 멀리갈 줄은"},
  {"time": "1:11", "line": "나의 손을 놓게 될 줄은"},
  {"time": "1:14", "line": "그대가 차갑게 변할 줄은 몰랐죠"},
  
  {"time": "1:21", "line": "어떻게 하죠"},
  {"time": "1:22.8", "line": "그대 가네요"},
  {"time": "1:25", "line": "잡을 수가 없어요"},
  {"time": "1:28", "line": "내가 바보였어요"},
  
  {"time": "1:48", "line": "우리 그러면 정말 그러면"},
  {"time": "1:51.5", "line": "서로를 이해 할 줄 알았죠"},
  {"time": "1:55", "line": "시간이 가면 웃게 될 줄 알았죠"},
  
  {"time": "2:01.8", "line": "떠나갈 줄은 멀리갈 줄은"},
  {"time": "2:04.9", "line": "나의 손을 놓게 될 줄은"},
  {"time": "2:08.5", "line": "그대가 차갑게 변할 줄은 몰랐죠"},
  
  {"time": "2:15", "line": "어떻게 하죠"},
  {"time": "2:17", "line": "그대 가네요"},
  {"time": "2:19", "line": "잡을 수가 없어요"},
  {"time": "2:22", "line": "내가 바보였나요"},
  
  {"time": "2:45.6", "line": "우리가 정말 헤어지나요"},
  {"time": "2:49", "line": "다시 볼 수 없게 되나요"},
  {"time": "2:52", "line": "꿈이죠 아니라고 해줘요 그렇죠"},
  
  {"time": "2:59", "line": "어떻게 하죠"},
  {"time": "3:01", "line": "그대 가네요 잡을 수가 없어요"},
  {"time": "3:06", "line": "이젠 볼 수 없나요"},
  
  {"time": "3:14.5", "line": "시간을 좀 가져요 잠시만 안녕해요"},
  {"time": "3:21", "line": "사랑도 가끔 쉬어야죠"},
  {"time": "3:28", "line": "서로를 놓아주고 잠시 한 숨 돌리면"},
  {"time": "3:35", "line": "더 나아질까요"}
]
