[
  { "time": 26.73, "line": "镌刻好每道眉间心上" },
  { "time": 35.46, "line": "画间透过思量" },
  { "time": 41.93, "line": "沾染了墨色淌" },
  { "time": 46.19, "line": "千家文都泛黄" },
  { "time": 51.03, "line": "夜静谧窗纱微微亮" },
  { "time": 65.59, "line": "拂袖起舞于梦中妩媚" },
  { "time": 73.64, "line": "相思蔓上心扉" },
  { "time": 80.41, "line": "她眷恋梨花泪" },
  { "time": 84.76, "line": "静画红妆等谁归" },
  { "time": 89.61, "line": "空留伊人徐徐憔悴" },
  { "time": 98.37, "line": "啊胭脂香味" },
  { "time": 106.06, "line": "卷珠帘是为谁" },
  { "time": 115.53, "line": "啊不见高轩" },
  { "time": 123.36, "line": "夜月明此时难为情" },
  { "time": 170.58, "line": "啊胭脂香味" },
  { "time": 179.00, "line": "卷珠帘是为谁" },
  { "time": 188.19, "line": "啊不见高轩" },
  { "time": 196.24, "line": "夜月明此时难为情" },
  { "time": 211.09, "line": "细雨落入初春的清晨" },
  { "time": 219.45, "line": "悄悄唤醒枝芽" },
  { "time": 226.26, "line": "听微风耳畔响" },
  { "time": 230.54, "line": "叹流水兮落花伤" },
  { "time": 237.87, "line": "谁在烟云处琴声长" }
]
